{"data":{"Year":[2016,2017,2018,2019,2020,2021,2022,2023,2024,2016,2017,2018,2019,2020,2021,2022,2023,2024,2016,2017,2018,2019,2020,2021,2022,2023,2024],"Sex":["Both Sexes","Both Sexes","Both Sexes","Both Sexes","Both Sexes","Both Sexes","Both Sexes","Both Sexes","Both Sexes","Females","Females","Females","Females","Females","Females","Females","Females","Females","Males","Males","Males","Males","Males","Males","Males","Males","Males"],"Value":[23.0,28.9,29.6,32.5,30.1,31.6,37.9,40.9,38.2,32.4,37.9,31.9,22.2,32.8,29.6,50.9,41.3,42.4,22.3,28.0,29.3,33.4,29.9,31.8,36.6,40.9,37.8]},"edges":[]}